{
	"name": "pipeline_copy_blob",
	"properties": {
		"activities": [
			{
				"name": "ForEach",
				"type": "ForEach",
				"dependsOn": [],
				"userProperties": [],
				"typeProperties": {
					"items": {
						"value": "@range(0, 1)",
						"type": "Expression"
					},
					"isSequential": true,
					"activities": [
						{
							"name": "get_all_data_api",
							"type": "Copy",
							"dependsOn": [],
							"policy": {
								"timeout": "0.12:00:00",
								"retry": 0,
								"retryIntervalInSeconds": 30,
								"secureOutput": false,
								"secureInput": false
							},
							"userProperties": [],
							"typeProperties": {
								"source": {
									"type": "RestSource",
									"httpRequestTimeout": "00:01:40",
									"requestInterval": "00.00:00:00.010",
									"requestMethod": "GET",
									"paginationRules": {
										"QueryParameters.{skip}": "RANGE:0:8676:20"
									}
								},
								"sink": {
									"type": "JsonSink",
									"storeSettings": {
										"type": "AzureBlobStorageWriteSettings",
										"copyBehavior": "PreserveHierarchy"
									},
									"formatSettings": {
										"type": "JsonWriteSettings"
									}
								},
								"enableStaging": false
							},
							"inputs": [
								{
									"referenceName": "RestResource_loop",
									"type": "DatasetReference"
								}
							],
							"outputs": [
								{
									"referenceName": "Json_output",
									"type": "DatasetReference"
								}
							]
						}
					]
				}
			}
		],
		"annotations": [],
		"lastPublishTime": "2024-04-25T11:07:39Z"
	},
	"type": "Microsoft.DataFactory/factories/pipelines"
}